arabic_parser.py
parser.py
lantools_nsa-0.0.2.dist-info/LICENSE.txt
lantools_nsa-0.0.2.dist-info/METADATA
lantools_nsa-0.0.2.dist-info/WHEEL
lantools_nsa-0.0.2.dist-info/top_level.txt
lantools_nsa-0.0.2.dist-info/RECORD
