Metadata-Version: 2.1
Name: lantools-nsa
Version: 0.0.2
Home-page: 
Author: Alaa' Omar
Author-email: 
License-File: LICENSE.txt
Requires-Dist: six (==1.16.0)
Requires-Dist: farasapy (==0.0.14)
Requires-Dist: tqdm (==4.62.2)
Requires-Dist: requests (==2.25.1)
Requires-Dist: regex (==2021.4.4)
Provides-Extra: dev
Requires-Dist: pytest (>=3.7) ; extra == 'dev'
Requires-Dist: check-manifest ; extra == 'dev'
Requires-Dist: twine ; extra == 'dev'
